Metadata-Version: 2.1
Name: UFANET
Version: 0.0.1
Summary: UFA-Net method proposed in paper Unsupervised Cross-Domain Functional MRI Adaptation for Automated Major Depressive Disorder Identification
Home-page: https://github.com/pypa/sampleproject
Author: Yuqi Fang
Author-email: yuqi9199@gmail.com
License: MIT
Platform: UNKNOWN
Classifier: Programming Language :: Python :: 3
Classifier: License :: OSI Approved :: MIT License
Classifier: Operating System :: OS Independent
Requires-Python: >=3.6
